discord/ext/dashboard/__init__.py
discord/ext/dashboard/dashboard.py
discord/ext/dashboard/errors.py
discord/ext/dashboard/server.py
discord_ext_dashboard-0.2.2.dist-info/LICENSE
discord_ext_dashboard-0.2.2.dist-info/METADATA
discord_ext_dashboard-0.2.2.dist-info/WHEEL
discord_ext_dashboard-0.2.2.dist-info/top_level.txt
discord_ext_dashboard-0.2.2.dist-info/RECORD
